tisp/__init__.py
tisp/branch_bound/__init__.py
tisp/branch_bound/branch_bound.py
tisp/branch_bound/branching.py
tisp/error.py
tisp/graph.py
tisp/heuristic/__init__.py
tisp/heuristic/compute.py
tisp/heuristic/lin_kernighan.py
tisp/heuristic.py
tisp/lp/__init__.py
tisp/lp/cut_relax.py
tisp/lp/model.py
tisp/lp/optimize.py
tisp/parser.py
tisp/resources.py
tisp/solver.py
tisp/tisp.py
tisp/tour.py
tisp/types.py
tisp-0.1.1.dist-info/METADATA
tisp-0.1.1.dist-info/WHEEL
tisp-0.1.1.dist-info/entry_points.txt
tisp-0.1.1.dist-info/RECORD
