Metadata-Version: 2.1
Name: tisp
Version: 0.1.1
Summary: Solve TSP instances to optimality.
Author: Tip ten Brink
Author-email: T.M.tenBrink@student.tudelft.nl
Requires-Python: >=3.9,<3.12
Classifier: Programming Language :: Python :: 3
Classifier: Programming Language :: Python :: 3.9
Classifier: Programming Language :: Python :: 3.10
Classifier: Programming Language :: Python :: 3.11
Requires-Dist: mip (>=1.15.0,<2.0.0)
